italian_tax_validators/__init__.py
italian_tax_validators/cli.py
italian_tax_validators/comuni.py
italian_tax_validators/validators.py
italian_tax_validators-1.1.0.dist-info/licenses/LICENSE.md
italian_tax_validators-1.1.0.dist-info/METADATA
italian_tax_validators-1.1.0.dist-info/WHEEL
italian_tax_validators-1.1.0.dist-info/entry_points.txt
italian_tax_validators-1.1.0.dist-info/top_level.txt
italian_tax_validators-1.1.0.dist-info/RECORD
