Metadata-Version: 2.4
Name: italian-tax-validators
Version: 1.1.0
Summary: Python library for validating Italian Codice Fiscale and Partita IVA
Author-email: Michele Broggi <michele@broggi.work>
License-Expression: MIT
Project-URL: Homepage, https://github.com/thesmokinator/italian-tax-validators
Project-URL: Documentation, https://github.com/thesmokinator/italian-tax-validators#readme
Project-URL: Repository, https://github.com/thesmokinator/italian-tax-validators.git
Project-URL: Issues, https://github.com/thesmokinator/italian-tax-validators/issues
Keywords: italian,codice-fiscale,partita-iva,tax-id,validation,fiscal-code,vat
Classifier: Development Status :: 5 - Production/Stable
Classifier: Intended Audience :: Developers
Classifier: Natural Language :: English
Classifier: Natural Language :: Italian
Classifier: Operating System :: OS Independent
Classifier: Programming Language :: Python
Classifier: Programming Language :: Python :: 3
Classifier: Programming Language :: Python :: 3.9
Classifier: Programming Language :: Python :: 3.10
Classifier: Programming Language :: Python :: 3.11
Classifier: Programming Language :: Python :: 3.12
Classifier: Programming Language :: Python :: 3.13
Classifier: Topic :: Software Development :: Libraries :: Python Modules
Classifier: Topic :: Office/Business :: Financial
Requires-Python: >=3.9
License-File: LICENSE.md
Dynamic: license-file
